typedpg/__init__.py
typedpg/cli.py
typedpg/decorator.py
typedpg/inference.py
typedpg/parser.py
typedpg/generators/__init__.py
typedpg/generators/dataclass_gen.py
typedpg/generators/pydantic_gen.py
typedpg-0.1.1.dist-info/METADATA
typedpg-0.1.1.dist-info/WHEEL
typedpg-0.1.1.dist-info/entry_points.txt
typedpg-0.1.1.dist-info/RECORD
