Metadata-Version: 2.4
Name: typedpg
Version: 0.1.1
Summary: Generate type-safe Python code from PostgreSQL queries
Project-URL: Homepage, https://github.com/jsegaran/typedpg
Project-URL: Repository, https://github.com/jsegaran/typedpg
Author: Joshua Segaran
License: MIT
Keywords: asyncpg,codegen,postgresql,psycopg,sql,typed
Classifier: Development Status :: 4 - Beta
Classifier: Intended Audience :: Developers
Classifier: License :: OSI Approved :: MIT License
Classifier: Programming Language :: Python :: 3
Classifier: Programming Language :: Python :: 3.11
Classifier: Programming Language :: Python :: 3.12
Classifier: Programming Language :: Python :: 3.13
Classifier: Topic :: Database
Classifier: Topic :: Software Development :: Code Generators
Classifier: Typing :: Typed
Requires-Python: >=3.11
Requires-Dist: asyncpg>=0.29.0
Requires-Dist: click>=8.0
Requires-Dist: pglast>=6.0
Requires-Dist: psycopg[binary]>=3.1.0
Requires-Dist: pydantic>=2.0
Requires-Dist: watchfiles>=0.21.0
Provides-Extra: dev
Requires-Dist: asyncpg-stubs>=0.29.0; extra == 'dev'
Requires-Dist: mypy>=1.8; extra == 'dev'
Requires-Dist: psycopg2-binary>=2.9.0; extra == 'dev'
Requires-Dist: pytest-asyncio>=0.23.0; extra == 'dev'
Requires-Dist: pytest>=8.0; extra == 'dev'
Requires-Dist: ruff>=0.3.0; extra == 'dev'
Requires-Dist: syrupy>=4.0; extra == 'dev'
Requires-Dist: testcontainers[postgres]>=4.0; extra == 'dev'
